[{"inputs":[{"internalType":"address[]","name":"targets","type":"address[]"},{"internalType":"uint256[]","name":"values","type":"uint256[]"},{"internalType":"bytes[]","name":"calldatas","type":"bytes[]"},{"internalType":"string","name":"description","type":"string"},{"internalType":"uint256","name":"startRoundId","type":"uint256"},{"internalType":"uint256","name":"depositAmount","type":"uint256"}],"name":"propose","outputs":[{"internalType":"uint256","name":"","type":"uint256"}],"stateMutability":"nonpayable","type":"function","$contractName":"VeBetterDAO-b3tr-governor"}]