[{"inputs":[{"internalType":"uint256","name":"","type":"uint256"}],"name":"degreeInfo","outputs":[{"internalType":"string","name":"recipientName","type":"string"},{"internalType":"string","name":"degreeType","type":"string"},{"internalType":"string","name":"issuingInstitution","type":"string"},{"internalType":"uint256","name":"dateOfIssuance","type":"uint256"},{"internalType":"string","name":"degreeNumber","type":"string"},{"internalType":"string","name":"academicRecordLink","type":"string"},{"internalType":"string","name":"metadata","type":"string"},{"internalType":"bool","name":"completedDiploma","type":"bool"},{"internalType":"bool","name":"isRevoked","type":"bool"},{"internalType":"uint256","name":"revocationDate","type":"uint256"},{"internalType":"bool","name":"isTransferred","type":"bool"}],"stateMutability":"view","type":"function","$contractName":"DiplomaToken"}]